Workbook

Sheet Dashboard
A1: @vssp | Controle Financeiro
A3: Vinicius Padovani 2026 | Dinheiro sem destino nao e liberdade. E caos com saldo positivo.
A5: ENTRADAS DO MES | C5: SAIDAS DO MES | E5: SALDO DO MES
A6: =SUMIF(Lancamentos!D5:D24,"Entrada",Lancamentos!E5:E24) -> 21694 | C6: =SUMIF(Lancamentos!D5:D24,"Saida",Lancamentos!E5:E24) -> 5630 | E6: =SUMIF(Lancamentos!D5:D24,"Entrada",Lancamentos!E5:E24)-SUMIF(Lancamentos!D5:D24,"Saida",Lancamentos!E5:E24) -> 16064
A8: RESUMO POR CATEGORIA
A9: Categoria | B9: Tipo | C9: Orcado | D9: Realizado | E9: Diferenca | F9: % Exec. | G9: Status
A10: =Categorias!A5 -> Atlas Logistica | B10: =Categorias!B5 -> Entrada | C10: =Categorias!C5 -> 12000 | D10: =Categorias!D5 -> 0 | E10: =Categorias!E5 -> 12000 | F10: =IF(Categorias!C5=0,0,Categorias!D5/Categorias!C5) -> 0 | G10: =Categorias!F5 -> Sem lancamentos
A11: =Categorias!A6 -> Primemobile | B11: =Categorias!B6 -> Entrada | C11: =Categorias!C6 -> 3000 | D11: =Categorias!D6 -> 0 | E11: =Categorias!E6 -> 3000 | F11: =IF(Categorias!C6=0,0,Categorias!D6/Categorias!C6) -> 0 | G11: =Categorias!F6 -> Sem lancamentos
A12: =Categorias!A7 -> Consultoria @vssp | B12: =Categorias!B7 -> Entrada | C12: =Categorias!C7 -> 1988 | D12: =Categorias!D7 -> 0 | E12: =Categorias!E7 -> 1988 | F12: =IF(Categorias!C7=0,0,Categorias!D7/Categorias!C7) -> 0 | G12: =Categorias!F7 -> Sem lancamentos
A13: =Categorias!A8 -> Grupo Villela | B13: =Categorias!B8 -> Entrada | C13: =Categorias!C8 -> 3000 | D13: =Categorias!D8 -> 0 | E13: =Categorias!E8 -> 3000 | F13: =IF(Categorias!C8=0,0,Categorias!D8/Categorias!C8) -> 0 | G13: =Categorias!F8 -> Sem lancamentos
A14: =Categorias!A9 -> Outros Entradas | B14: =Categorias!B9 -> Entrada | C14: =Categorias!C9 -> 500 | D14: =Categorias!D9 -> 0 | E14: =Categorias!E9 -> 500 | F14: =IF(Categorias!C9=0,0,Categorias!D9/Categorias!C9) -> 0 | G14: =Categorias!F9 -> Sem lancamentos
A15: =Categorias!A10 -> Moradia | B15: =Categorias!B10 -> Saida | C15: =Categorias!C10 -> 2100 | D15: =Categorias!D10 -> 1980 | E15: =Categorias!E10 -> 120 | F15: =IF(Categorias!C10=0,0,Categorias!D10/Categorias!C10) -> 0.94285714 | G15: =Categorias!F10 -> Dentro do orcamento
A16: =Categorias!A11 -> Alimentacao | B16: =Categorias!B11 -> Saida | C16: =Categorias!C11 -> 800 | D16: =Categorias!D11 -> 755 | E16: =Categorias!E11 -> 45 | F16: =IF(Categorias!C11=0,0,Categorias!D11/Categorias!C11) -> 0.94375 | G16: =Categorias!F11 -> Dentro do orcamento
A17: =Categorias!A12 -> Transporte | B17: =Categorias!B12 -> Saida | C17: =Categorias!C12 -> 500 | D17: =Categorias!D12 -> 400 | E17: =Categorias!E12 -> 100 | F17: =IF(Categorias!C12=0,0,Categorias!D12/Categorias!C12) -> 0.8 | G17: =Categorias!F12 -> Dentro do orcamento
A18: =Categorias!A13 -> Saude | B18: =Categorias!B13 -> Saida | C18: =Categorias!C13 -> 650 | D18: =Categorias!D13 -> 600 | E18: =Categorias!E13 -> 50 | F18: =IF(Categorias!C13=0,0,Categorias!D13/Categorias!C13) -> 0.92307692 | G18: =Categorias!F13 -> Dentro do orcamento
A19: =Categorias!A14 -> Educacao | B19: =Categorias!B14 -> Saida | C19: =Categorias!C14 -> 300 | D19: =Categorias!D14 -> 120 | E19: =Categorias!E14 -> 180 | F19: =IF(Categorias!C14=0,0,Categorias!D14/Categorias!C14) -> 0.4 | G19: =Categorias!F14 -> Dentro do orcamento
A20: =Categorias!A15 -> Lazer | B20: =Categorias!B15 -> Saida | C20: =Categorias!C15 -> 400 | D20: =Categorias!D15 -> 0 | E20: =Categorias!E15 -> 400 | F20: =IF(Categorias!C15=0,0,Categorias!D15/Categorias!C15) -> 0 | G20: =Categorias!F15 -> Sem lancamentos
A21: =Categorias!A16 -> Negocios | B21: =Categorias!B16 -> Saida | C21: =Categorias!C16 -> 1000 | D21: =Categorias!D16 -> 775 | E21: =Categorias!E16 -> 225 | F21: =IF(Categorias!C16=0,0,Categorias!D16/Categorias!C16) -> 0.775 | G21: =Categorias!F16 -> Dentro do orcamento
... A24: =Categorias!A19 -> Outros Saidas | B24: =Categorias!B19 -> Saida | C24: =Categorias!C19 -> 200 | D24: =Categorias!D19 -> 0 | E24: =Categorias!E19 -> 200 | F24: =IF(Categorias!C19=0,0,Categorias!D19/Categorias!C19) -> 0 | G24: =Categorias!F19 -> Sem lancamentos
A26: Adicione seus lancamentos na aba 'Lancamentos'. Este dashboard atualiza automaticamente.

Sheet Lancamentos
A1: @vssp - Controle Financeiro - Lancamentos
A2: Registre cada entrada e saida. O Dashboard atualiza automaticamente.
A4: Data | B4: Descricao | C4: Categoria | D4: Tipo | E4: Valor (R$) | F4: Mes/Ano | G4: Observacao | H4: Status
A5: 01/04/2026 | B5: Atlas Logistica - Repasse mensal | C5: Servico | D5: Entrada | E5: 12000 | F5: 04/2026 | H5: Confirmado
A6: 01/04/2026 | B6: Aluguel | C6: Moradia | D6: Saida | E6: 1800 | F6: 04/2026 | H6: Confirmado
A7: 02/04/2026 | B7: Supermercado | C7: Alimentacao | D7: Saida | E7: 380 | F7: 04/2026 | H7: Confirmado
A8: 03/04/2026 | B8: Comissao Grupo Villela | C8: Comissao | D8: Entrada | E8: 3200 | F8: 04/2026 | H8: Confirmado
A9: 04/04/2026 | B9: Combustivel | C9: Transporte | D9: Saida | E9: 220 | F9: 04/2026 | H9: Confirmado
A10: 05/04/2026 | B10: Primemobile - Venda | C10: Venda | D10: Entrada | E10: 1500 | F10: 04/2026 | H10: Confirmado
A11: 06/04/2026 | B11: Plano de saude | C11: Saude | D11: Saida | E11: 450 | F11: 04/2026 | H11: Confirmado
A12: 07/04/2026 | B12: Restaurante | C12: Alimentacao | D12: Saida | E12: 85 | F12: 04/2026 | H12: Confirmado
A13: 08/04/2026 | B13: Academia | C13: Saude | D13: Saida | E13: 150 | F13: 04/2026 | H13: Confirmado
A14: 09/04/2026 | B14: Consultoria @vssp - Sessao 1 | C14: Servico | D14: Entrada | E14: 497 | F14: 04/2026 | H14: Confirmado
A15: 10/04/2026 | B15: Manutencao veiculo Atlas | C15: Negocios | D15: Saida | E15: 680 | F15: 04/2026 | H15: Confirmado
A16: 11/04/2026 | B16: Consultoria @vssp - Sessao 2 | C16: Servico | D16: Entrada | E16: 497 | F16: 04/2026 | H16: Confirmado
... A24: 22/04/2026 | B24: Material de escritorio | C24: Negocios | D24: Saida | E24: 95 | F24: 04/2026 | H24: Confirmado
B26: Total Entradas: | E26: =SUMIF(D5:D24,"Entrada",E5:E24) -> 21694
B27: Total Saidas: | E27: =SUMIF(D5:D24,"Saida",E5:E24) -> 5630
B28: Saldo do Mes: | E28: =E26-E27 -> 16064

Sheet Categorias
A1: @vssp - Orcamento por Categoria
A2: Defina o orcamento mensal e acompanhe o realizado.
A4: Categoria | B4: Tipo | C4: Orcamento (R$) | D4: Realizado (R$) | E4: Diferenca (R$) | F4: Status
A5: Atlas Logistica | B5: Entrada | C5: 12000 | D5: =SUMIFS(Lancamentos!E5:E24,Lancamentos!C5:C24,A5,Lancamentos!D5:D24,B5) -> 0 | E5: =C5-D5 -> 12000 | F5: =IF(D5=0,"Sem lancamentos",IF(D5<=C5,"Dentro do orcamento","Acima do orcamento")) -> Sem lancamentos
A6: Primemobile | B6: Entrada | C6: 3000 | D6: =SUMIFS(Lancamentos!E5:E24,Lancamentos!C5:C24,A6,Lancamentos!D5:D24,B6) -> 0 | E6: =C6-D6 -> 3000 | F6: =IF(D6=0,"Sem lancamentos",IF(D6<=C6,"Dentro do orcamento","Acima do orcamento")) -> Sem lancamentos
A7: Consultoria @vssp | B7: Entrada | C7: 1988 | D7: =SUMIFS(Lancamentos!E5:E24,Lancamentos!C5:C24,A7,Lancamentos!D5:D24,B7) -> 0 | E7: =C7-D7 -> 1988 | F7: =IF(D7=0,"Sem lancamentos",IF(D7<=C7,"Dentro do orcamento","Acima do orcamento")) -> Sem lancamentos
A8: Grupo Villela | B8: Entrada | C8: 3000 | D8: =SUMIFS(Lancamentos!E5:E24,Lancamentos!C5:C24,A8,Lancamentos!D5:D24,B8) -> 0 | E8: =C8-D8 -> 3000 | F8: =IF(D8=0,"Sem lancamentos",IF(D8<=C8,"Dentro do orcamento","Acima do orcamento")) -> Sem lancamentos
A9: Outros Entradas | B9: Entrada | C9: 500 | D9: =SUMIFS(Lancamentos!E5:E24,Lancamentos!C5:C24,A9,Lancamentos!D5:D24,B9) -> 0 | E9: =C9-D9 -> 500 | F9: =IF(D9=0,"Sem lancamentos",IF(D9<=C9,"Dentro do orcamento","Acima do orcamento")) -> Sem lancamentos
A10: Moradia | B10: Saida | C10: 2100 | D10: =SUMIFS(Lancamentos!E5:E24,Lancamentos!C5:C24,A10,Lancamentos!D5:D24,B10) -> 1980 | E10: =C10-D10 -> 120 | F10: =IF(D10=0,"Sem lancamentos",IF(D10<=C10,"Dentro do orcamento","Acima do orcamento")) -> Dentro do orcamento
A11: Alimentacao | B11: Saida | C11: 800 | D11: =SUMIFS(Lancamentos!E5:E24,Lancamentos!C5:C24,A11,Lancamentos!D5:D24,B11) -> 755 | E11: =C11-D11 -> 45 | F11: =IF(D11=0,"Sem lancamentos",IF(D11<=C11,"Dentro do orcamento","Acima do orcamento")) -> Dentro do orcamento
A12: Transporte | B12: Saida | C12: 500 | D12: =SUMIFS(Lancamentos!E5:E24,Lancamentos!C5:C24,A12,Lancamentos!D5:D24,B12) -> 400 | E12: =C12-D12 -> 100 | F12: =IF(D12=0,"Sem lancamentos",IF(D12<=C12,"Dentro do orcamento","Acima do orcamento")) -> Dentro do orcamento
A13: Saude | B13: Saida | C13: 650 | D13: =SUMIFS(Lancamentos!E5:E24,Lancamentos!C5:C24,A13,Lancamentos!D5:D24,B13) -> 600 | E13: =C13-D13 -> 50 | F13: =IF(D13=0,"Sem lancamentos",IF(D13<=C13,"Dentro do orcamento","Acima do orcamento")) -> Dentro do orcamento
A14: Educacao | B14: Saida | C14: 300 | D14: =SUMIFS(Lancamentos!E5:E24,Lancamentos!C5:C24,A14,Lancamentos!D5:D24,B14) -> 120 | E14: =C14-D14 -> 180 | F14: =IF(D14=0,"Sem lancamentos",IF(D14<=C14,"Dentro do orcamento","Acima do orcamento")) -> Dentro do orcamento
A15: Lazer | B15: Saida | C15: 400 | D15: =SUMIFS(Lancamentos!E5:E24,Lancamentos!C5:C24,A15,Lancamentos!D5:D24,B15) -> 0 | E15: =C15-D15 -> 400 | F15: =IF(D15=0,"Sem lancamentos",IF(D15<=C15,"Dentro do orcamento","Acima do orcamento")) -> Sem lancamentos
A16: Negocios | B16: Saida | C16: 1000 | D16: =SUMIFS(Lancamentos!E5:E24,Lancamentos!C5:C24,A16,Lancamentos!D5:D24,B16) -> 775 | E16: =C16-D16 -> 225 | F16: =IF(D16=0,"Sem lancamentos",IF(D16<=C16,"Dentro do orcamento","Acima do orcamento")) -> Dentro do orcamento
A17: Investimento | B17: Saida | C17: 2000 | D17: =SUMIFS(Lancamentos!E5:E24,Lancamentos!C5:C24,A17,Lancamentos!D5:D24,B17) -> 1000 | E17: =C17-D17 -> 1000 | F17: =IF(D17=0,"Sem lancamentos",IF(D17<=C17,"Dentro do orcamento","Acima do orcamento")) -> Dentro do orcamento
A18: Pessoal | B18: Saida | C18: 300 | D18: =SUMIFS(Lancamentos!E5:E24,Lancamentos!C5:C24,A18,Lancamentos!D5:D24,B18) -> 0 | E18: =C18-D18 -> 300 | F18: =IF(D18=0,"Sem lancamentos",IF(D18<=C18,"Dentro do orcamento","Acima do orcamento")) -> Sem lancamentos
A19: Outros Saidas | B19: Saida | C19: 200 | D19: =SUMIFS(Lancamentos!E5:E24,Lancamentos!C5:C24,A19,Lancamentos!D5:D24,B19) -> 0 | E19: =C19-D19 -> 200 | F19: =IF(D19=0,"Sem lancamentos",IF(D19<=C19,"Dentro do orcamento","Acima do orcamento")) -> Sem lancamentos
